debian_inspector/__init__.py
debian_inspector/contents.py
debian_inspector/copyright.py
debian_inspector/coverage.py
debian_inspector/deb822.py
debian_inspector/debcon.py
debian_inspector/deps.py
debian_inspector/mit.LICENSE
debian_inspector/package.py
debian_inspector/unsign.py
debian_inspector/unsign.py.ABOUT
debian_inspector/unsign.py.LICENSE
debian_inspector/utils.py
debian_inspector/version.py
debian_inspector/version.py.ABOUT
debian_inspector/version.py.LICENSE
debian_inspector-31.1.0.dist-info/CHANGELOG.rst
debian_inspector-31.1.0.dist-info/CODE_OF_CONDUCT.rst
debian_inspector-31.1.0.dist-info/METADATA
debian_inspector-31.1.0.dist-info/NOTICE
debian_inspector-31.1.0.dist-info/WHEEL
debian_inspector-31.1.0.dist-info/apache-2.0.LICENSE
debian_inspector-31.1.0.dist-info/top_level.txt
debian_inspector-31.1.0.dist-info/RECORD
