Metadata-Version: 2.1
Name: debian_inspector
Version: 31.1.0
Summary: Utilities to parse Debian package, copyright and control files.
Home-page: https://github.com/nexB/debian-inspector
Author: nexB. Inc. and others
Author-email: info@aboutcode.org
License: Apache-2.0 AND BSD-3-Clause AND MIT
Keywords: utilities,deb822,debian,copyright,package,dependency,license,dep5,control,dsc,python-debian,dpkg,libapt
Classifier: Development Status :: 5 - Production/Stable
Classifier: Intended Audience :: Developers
Classifier: Programming Language :: Python :: 3
Classifier: Programming Language :: Python :: 3 :: Only
Classifier: Programming Language :: Python :: 3.6
Classifier: Programming Language :: Python :: 3.7
Classifier: Programming Language :: Python :: 3.8
Classifier: Programming Language :: Python :: 3.9
Classifier: Programming Language :: Python :: 3.10
Classifier: Topic :: Software Development
Classifier: Topic :: Utilities
Requires-Python: >=3.7
License-File: apache-2.0.LICENSE
License-File: NOTICE
License-File: CHANGELOG.rst
License-File: CODE_OF_CONDUCT.rst
Requires-Dist: chardet >=3.0.0
Requires-Dist: attrs !=20.1.0,>=19.2
Provides-Extra: docs
Requires-Dist: Sphinx >=5.0.2 ; extra == 'docs'
Requires-Dist: sphinx-rtd-theme >=1.0.0 ; extra == 'docs'
Requires-Dist: sphinx-reredirects >=0.1.2 ; extra == 'docs'
Requires-Dist: sphinxcontrib-apidoc >=0.3.0 ; extra == 'docs'
Requires-Dist: doc8 >=0.11.2 ; extra == 'docs'
Requires-Dist: sphinx-autobuild ; extra == 'docs'
Requires-Dist: sphinx-rtd-dark-mode >=1.3.0 ; extra == 'docs'
Requires-Dist: sphinx-copybutton ; extra == 'docs'
Provides-Extra: testing
Requires-Dist: pytest !=7.0.0,>=6 ; extra == 'testing'
Requires-Dist: pytest-xdist >=2 ; extra == 'testing'
Requires-Dist: aboutcode-toolkit >=7.0.2 ; extra == 'testing'
Requires-Dist: pycodestyle >=2.8.0 ; extra == 'testing'
Requires-Dist: twine ; extra == 'testing'
Requires-Dist: black ; extra == 'testing'
Requires-Dist: commoncode ; extra == 'testing'
Requires-Dist: isort ; extra == 'testing'
